{
  "sources": {
    "affidavit": "https://myneta.info/Jharkhand2024/ (ADR / MyNeta)"
  },
  "house": "Jharkhand Legislative Assembly",
  "stateName": "Jharkhand",
  "stateSlug": "jharkhand",
  "scrapedAt": "2026-07-14T09:32:55.231Z",
  "count": 73,
  "records": [
    {
      "id": "991",
      "name": "Amit Kumar",
      "constituency": "SILLI",
      "state": "Jharkhand",
      "stateSlug": "jharkhand",
      "party": "JMM",
      "criminalCases": 8,
      "education": "Graduate Professional",
      "assets": 15417195,
      "liabilities": 0,
      "sourceUrl": "https://myneta.info/Jharkhand2024/candidate.php?candidate_id=991",
      "prs": null,
      "photoUrl": "https://myneta.info/images_candidate/Jharkhand2024/91ac848a3c700b6e760ac2f5fa32800822147ce2.jpg"
    },
    {
      "id": "249",
      "name": "Amit Kumar Yadav",
      "constituency": "BARKATHA",
      "state": "Jharkhand",
      "stateSlug": "jharkhand",
      "party": "BJP",
      "criminalCases": 1,
      "education": "Graduate",
      "assets": 41478055,
      "liabilities": 5312700,
      "sourceUrl": "https://myneta.info/Jharkhand2024/candidate.php?candidate_id=249",
      "prs": null,
      "photoUrl": "https://myneta.info/images_candidate/Jharkhand2024/dd14ebd6cba93f401f10aa4641823edd37281a93.jpg"
    },
    {
      "id": "8",
      "name": "Anant Pratap Deo",
      "constituency": "BHAWANATHPUR",
      "state": "Jharkhand",
      "stateSlug": "jharkhand",
      "party": "JMM",
      "criminalCases": 2,
      "education": "12th Pass",
      "assets": 169467000,
      "liabilities": 0,
      "sourceUrl": "https://myneta.info/Jharkhand2024/candidate.php?candidate_id=8",
      "prs": null,
      "photoUrl": "https://myneta.info/images_candidate/Jharkhand2024/cde02c0458456cac882e4e3791f494cd5e0dfdc3.jpg"
    },
    {
      "id": "822",
      "name": "Arup Chatterjee",
      "constituency": "NIRSA",
      "state": "Jharkhand",
      "stateSlug": "jharkhand",
      "party": "CPI(ML)(L)",
      "criminalCases": 5,
      "education": "Graduate",
      "assets": 60820403,
      "liabilities": 616000,
      "sourceUrl": "https://myneta.info/Jharkhand2024/candidate.php?candidate_id=822",
      "prs": null,
      "photoUrl": "https://myneta.info/images_candidate/Jharkhand2024/1b7fd4a90e294a8731fe11e04076adfb7d9aa22a.jpg"
    },
    {
      "id": "1251",
      "name": "Babu Lal Marandi",
      "constituency": "DHANWAR",
      "state": "Jharkhand",
      "stateSlug": "jharkhand",
      "party": "BJP",
      "criminalCases": 15,
      "education": "Graduate",
      "assets": 19461396,
      "liabilities": 0,
      "sourceUrl": "https://myneta.info/Jharkhand2024/candidate.php?candidate_id=1251",
      "prs": null,
      "photoUrl": "https://myneta.info/images_candidate/Jharkhand2024/81a05b83885030b751d435e320d83ce09b35fe54.jpg"
    },
    {
      "id": "831",
      "name": "Basant Soren",
      "constituency": "DUMKA (ST)",
      "state": "Jharkhand",
      "stateSlug": "jharkhand",
      "party": "JMM",
      "criminalCases": 0,
      "education": "10th Pass",
      "assets": 126872256,
      "liabilities": 11054291,
      "sourceUrl": "https://myneta.info/Jharkhand2024/candidate.php?candidate_id=831",
      "prs": null,
      "photoUrl": "https://myneta.info/images_candidate/Jharkhand2024/e2c19e4d11c66740e1c73073b4ef9654f3d0a2a3.jpg"
    },
    {
      "id": "375",
      "name": "Bhushan Bara",
      "constituency": "SIMDEGA (ST)",
      "state": "Jharkhand",
      "stateSlug": "jharkhand",
      "party": "INC",
      "criminalCases": 1,
      "education": "Graduate",
      "assets": 12462945,
      "liabilities": 4920640,
      "sourceUrl": "https://myneta.info/Jharkhand2024/candidate.php?candidate_id=375",
      "prs": null,
      "photoUrl": "https://myneta.info/images_candidate/Jharkhand2024/d1860f54d03a77750e43ce7bf3970e2d907e584c.jpg"
    },
    {
      "id": "230",
      "name": "Bhushan Tirkey",
      "constituency": "GUMLA (ST)",
      "state": "Jharkhand",
      "stateSlug": "jharkhand",
      "party": "JMM",
      "criminalCases": 2,
      "education": "10th Pass",
      "assets": 58056488,
      "liabilities": 1141120,
      "sourceUrl": "https://myneta.info/Jharkhand2024/candidate.php?candidate_id=230",
      "prs": null,
      "photoUrl": "https://myneta.info/images_candidate/Jharkhand2024/f6e44fefda32ec9358521d40d886260d79694421.jpg"
    },
    {
      "id": "734",
      "name": "Champai Soren",
      "constituency": "SERAIKELLA (ST)",
      "state": "Jharkhand",
      "stateSlug": "jharkhand",
      "party": "BJP",
      "criminalCases": 1,
      "education": "10th Pass",
      "assets": 33665117,
      "liabilities": 3981164,
      "sourceUrl": "https://myneta.info/Jharkhand2024/candidate.php?candidate_id=734",
      "prs": null,
      "photoUrl": "https://myneta.info/images_candidate/Jharkhand2024/9394a38fc146d8794e3982aa504794a61f91f0c4.jpg"
    },
    {
      "id": "311",
      "name": "Chamra Linda",
      "constituency": "BISHUNPUR (ST)",
      "state": "Jharkhand",
      "stateSlug": "jharkhand",
      "party": "JMM",
      "criminalCases": 1,
      "education": "Graduate",
      "assets": 28070895,
      "liabilities": 3573368,
      "sourceUrl": "https://myneta.info/Jharkhand2024/candidate.php?candidate_id=311",
      "prs": null,
      "photoUrl": "https://myneta.info/images_candidate/Jharkhand2024/9b988940731b0bfd1dbba8d60d4517103b47a560.jpg"
    },
    {
      "id": "934",
      "name": "Chandradeo Mahato Alias Bablu Mahato",
      "constituency": "SINDRI",
      "state": "Jharkhand",
      "stateSlug": "jharkhand",
      "party": "CPI(ML)(L)",
      "criminalCases": 2,
      "education": "Post Graduate",
      "assets": 17564026,
      "liabilities": 555940,
      "sourceUrl": "https://myneta.info/Jharkhand2024/candidate.php?candidate_id=934",
      "prs": null,
      "photoUrl": "https://myneta.info/images_candidate/Jharkhand2024/f6bceb4939403394e3b58cd04b0e4a35b8d88819.jpg"
    },
    {
      "id": "342",
      "name": "Chandreshwar Prasad Singh",
      "constituency": "RANCHI",
      "state": "Jharkhand",
      "stateSlug": "jharkhand",
      "party": "BJP",
      "criminalCases": 2,
      "education": "Graduate Professional",
      "assets": 102350394,
      "liabilities": 5080000,
      "sourceUrl": "https://myneta.info/Jharkhand2024/candidate.php?candidate_id=342",
      "prs": null,
      "photoUrl": "https://myneta.info/images_candidate/Jharkhand2024/2842cb8a23686f5c59c68d87a19322c31c4fc6c7.jpg"
    },
    {
      "id": "139",
      "name": "Deepak Birua",
      "constituency": "CHAIBASA (ST)",
      "state": "Jharkhand",
      "stateSlug": "jharkhand",
      "party": "JMM",
      "criminalCases": 0,
      "education": "Graduate",
      "assets": 31234358,
      "liabilities": 0,
      "sourceUrl": "https://myneta.info/Jharkhand2024/candidate.php?candidate_id=139",
      "prs": null,
      "photoUrl": "https://myneta.info/images_candidate/Jharkhand2024/8a092a0292636808b7bdeabc1ceadc0f40e548ad.jpg"
    },
    {
      "id": "1258",
      "name": "Devendra Kunwar",
      "constituency": "JARMUNDI",
      "state": "Jharkhand",
      "stateSlug": "jharkhand",
      "party": "BJP",
      "criminalCases": 0,
      "education": "10th Pass",
      "assets": 56370219,
      "liabilities": 954178,
      "sourceUrl": "https://myneta.info/Jharkhand2024/candidate.php?candidate_id=1258",
      "prs": null,
      "photoUrl": "https://myneta.info/images_candidate/Jharkhand2024/abd6fc05b0f204d9adbfb78d34fcef3c3e25e0b2.jpg"
    },
    {
      "id": "892",
      "name": "Dhananjay Soren",
      "constituency": "BORIO (ST)",
      "state": "Jharkhand",
      "stateSlug": "jharkhand",
      "party": "JMM",
      "criminalCases": 0,
      "education": "10th Pass",
      "assets": 6584416,
      "liabilities": 710000,
      "sourceUrl": "https://myneta.info/Jharkhand2024/candidate.php?candidate_id=892",
      "prs": null,
      "photoUrl": "https://myneta.info/images_candidate/Jharkhand2024/5d4b324c971970f387f67b2b8b900fb40589323d.jpg"
    },
    {
      "id": "801",
      "name": "Dr. Neera Yadav",
      "constituency": "KODARMA",
      "state": "Jharkhand",
      "stateSlug": "jharkhand",
      "party": "BJP",
      "criminalCases": 1,
      "education": "Doctorate",
      "assets": 47908811,
      "liabilities": 2778220,
      "sourceUrl": "https://myneta.info/Jharkhand2024/candidate.php?candidate_id=801",
      "prs": null,
      "photoUrl": "https://myneta.info/images_candidate/Jharkhand2024/9fa3ab0b757955ec0b2f0874e1efbea87ec864ea.jpg"
    },
    {
      "id": "919",
      "name": "Hafizul Hassan",
      "constituency": "MADHUPUR",
      "state": "Jharkhand",
      "stateSlug": "jharkhand",
      "party": "JMM",
      "criminalCases": 0,
      "education": "Others",
      "assets": 16031767,
      "liabilities": 0,
      "sourceUrl": "https://myneta.info/Jharkhand2024/candidate.php?candidate_id=919",
      "prs": null,
      "photoUrl": "https://myneta.info/images_candidate/Jharkhand2024/d4f2a4230700346a9fbc981554818108bccdd8d8.jpg"
    },
    {
      "id": "895",
      "name": "Hemant Soren",
      "constituency": "BARHAIT (ST)",
      "state": "Jharkhand",
      "stateSlug": "jharkhand",
      "party": "JMM",
      "criminalCases": 5,
      "education": "12th Pass",
      "assets": 253387953,
      "liabilities": 39263081,
      "sourceUrl": "https://myneta.info/Jharkhand2024/candidate.php?candidate_id=895",
      "prs": null,
      "photoUrl": "https://myneta.info/images_candidate/Jharkhand2024/8c7332b31a80880e2e67c74c2cdd1561b371c0ed.jpg"
    },
    {
      "id": "976",
      "name": "Hemlal Murmu",
      "constituency": "LITIPARA (ST)",
      "state": "Jharkhand",
      "stateSlug": "jharkhand",
      "party": "JMM",
      "criminalCases": 0,
      "education": "Graduate",
      "assets": 46061803,
      "liabilities": 24091459,
      "sourceUrl": "https://myneta.info/Jharkhand2024/candidate.php?candidate_id=976",
      "prs": null,
      "photoUrl": "https://myneta.info/images_candidate/Jharkhand2024/d4eceaf78a518bc6bdadf638c0a9bd797eda38b3.jpg"
    },
    {
      "id": "872",
      "name": "Irfan Ansari",
      "constituency": "JAMTARA",
      "state": "Jharkhand",
      "stateSlug": "jharkhand",
      "party": "INC",
      "criminalCases": 5,
      "education": "Post Graduate",
      "assets": 35281427,
      "liabilities": 3000000,
      "sourceUrl": "https://myneta.info/Jharkhand2024/candidate.php?candidate_id=872",
      "prs": null,
      "photoUrl": "https://myneta.info/images_candidate/Jharkhand2024/2f2fee3adf0df5ddf37993ec9c8db94cb74baab1.jpg"
    },
    {
      "id": "144",
      "name": "Jagat Majhi",
      "constituency": "MANOHARPUR (ST)",
      "state": "Jharkhand",
      "stateSlug": "jharkhand",
      "party": "JMM",
      "criminalCases": 0,
      "education": "Graduate",
      "assets": 9688458,
      "liabilities": 1548416,
      "sourceUrl": "https://myneta.info/Jharkhand2024/candidate.php?candidate_id=144",
      "prs": null,
      "photoUrl": "https://myneta.info/images_candidate/Jharkhand2024/065e400798c4120f638827d2b138e3914a41f7ed.jpg"
    },
    {
      "id": "855",
      "name": "Jairam Kumar Mahato",
      "constituency": "DUMRI",
      "state": "Jharkhand",
      "stateSlug": "jharkhand",
      "party": "Jharkhand Loktantrik Krantikari Morcha",
      "criminalCases": 14,
      "education": "Post Graduate",
      "assets": 255965,
      "liabilities": 0,
      "sourceUrl": "https://myneta.info/Jharkhand2024/candidate.php?candidate_id=855",
      "prs": null,
      "photoUrl": "https://myneta.info/images_candidate/Jharkhand2024/5db0e91ddc76b3a4046a4aef090a114c0fe7a03f.jpg"
    },
    {
      "id": "175",
      "name": "Janardhan Paswan",
      "constituency": "CHATRA (SC)",
      "state": "Jharkhand",
      "stateSlug": "jharkhand",
      "party": "Lok Janshakti Party(Ram Vilas)",
      "criminalCases": 2,
      "education": "Graduate",
      "assets": 24263292,
      "liabilities": 5294000,
      "sourceUrl": "https://myneta.info/Jharkhand2024/candidate.php?candidate_id=175",
      "prs": null,
      "photoUrl": "https://myneta.info/images_candidate/Jharkhand2024/4a1cbddd4325f32523b0282620de48c4bbfae150.jpg"
    },
    {
      "id": "227",
      "name": "Jiga Susaran Horo",
      "constituency": "SISAI (ST)",
      "state": "Jharkhand",
      "stateSlug": "jharkhand",
      "party": "JMM",
      "criminalCases": 1,
      "education": "10th Pass",
      "assets": 13124776,
      "liabilities": 0,
      "sourceUrl": "https://myneta.info/Jharkhand2024/candidate.php?candidate_id=227",
      "prs": null,
      "photoUrl": "https://myneta.info/images_candidate/Jharkhand2024/c424f9790d9e6b441eb9d0048e8e2c9c771b0751.jpg"
    },
    {
      "id": "849",
      "name": "Kalpana Murmu Soren",
      "constituency": "GANDEY",
      "state": "Jharkhand",
      "stateSlug": "jharkhand",
      "party": "JMM",
      "criminalCases": 0,
      "education": "Post Graduate",
      "assets": 253387953,
      "liabilities": 39263081,
      "sourceUrl": "https://myneta.info/Jharkhand2024/candidate.php?candidate_id=849",
      "prs": null,
      "photoUrl": "https://myneta.info/images_candidate/Jharkhand2024/2f501d8ab907278fdc0c721631d1718533780520.jpg"
    },
    {
      "id": "149",
      "name": "Kumar Ujjwal",
      "constituency": "SIMARIA (SC)",
      "state": "Jharkhand",
      "stateSlug": "jharkhand",
      "party": "BJP",
      "criminalCases": 0,
      "education": "Post Graduate",
      "assets": 152222000,
      "liabilities": 3267700,
      "sourceUrl": "https://myneta.info/Jharkhand2024/candidate.php?candidate_id=149",
      "prs": null,
      "photoUrl": "https://myneta.info/images_candidate/Jharkhand2024/835e168d80bb491c82ccb706da4d09ede3c43dbf.jpg"
    },
    {
      "id": "19",
      "name": "Kushwaha Shashi Bhushan Mehta",
      "constituency": "PANKI",
      "state": "Jharkhand",
      "stateSlug": "jharkhand",
      "party": "BJP",
      "criminalCases": 9,
      "education": "Doctorate",
      "assets": 321546244,
      "liabilities": 5640000,
      "sourceUrl": "https://myneta.info/Jharkhand2024/candidate.php?candidate_id=19",
      "prs": null,
      "photoUrl": "https://myneta.info/images_candidate/Jharkhand2024/66896aa298275a484e994b357e81a328777e965f.jpg"
    },
    {
      "id": "989",
      "name": "Mamta Devi",
      "constituency": "RAMGARH",
      "state": "Jharkhand",
      "stateSlug": "jharkhand",
      "party": "INC",
      "criminalCases": 3,
      "education": "Graduate",
      "assets": 11698907,
      "liabilities": 1060000,
      "sourceUrl": "https://myneta.info/Jharkhand2024/candidate.php?candidate_id=989",
      "prs": null,
      "photoUrl": "https://myneta.info/images_candidate/Jharkhand2024/72b98d6f28d167d30fb5ddf139212dc18ccb908b.jpg"
    },
    {
      "id": "16",
      "name": "Mangal Kalindi",
      "constituency": "JUGSALAI (SC)",
      "state": "Jharkhand",
      "stateSlug": "jharkhand",
      "party": "JMM",
      "criminalCases": 0,
      "education": "10th Pass",
      "assets": 9011330,
      "liabilities": 3200000,
      "sourceUrl": "https://myneta.info/Jharkhand2024/candidate.php?candidate_id=16",
      "prs": null,
      "photoUrl": "https://myneta.info/images_candidate/Jharkhand2024/182b2234ea260278f0a86cf1a782191db891299b.jpg"
    },
    {
      "id": "846",
      "name": "Manju Kumari",
      "constituency": "JAMUA (SC)",
      "state": "Jharkhand",
      "stateSlug": "jharkhand",
      "party": "BJP",
      "criminalCases": 0,
      "education": "10th Pass",
      "assets": 2187000,
      "liabilities": 200000,
      "sourceUrl": "https://myneta.info/Jharkhand2024/candidate.php?candidate_id=846",
      "prs": null,
      "photoUrl": "https://myneta.info/images_candidate/Jharkhand2024/8139bf4fabda29c655b192507a434339ca642b68.jpg"
    },
    {
      "id": "255",
      "name": "Manoj Kumar Yadav",
      "constituency": "BARHI",
      "state": "Jharkhand",
      "stateSlug": "jharkhand",
      "party": "BJP",
      "criminalCases": 12,
      "education": "Graduate",
      "assets": 82807143,
      "liabilities": 3820959,
      "sourceUrl": "https://myneta.info/Jharkhand2024/candidate.php?candidate_id=255",
      "prs": null,
      "photoUrl": "https://myneta.info/images_candidate/Jharkhand2024/52998ee4a6d6399cb0e3d0b5eb5e216b8cade06a.jpg"
    },
    {
      "id": "828",
      "name": "Mathura Prasad Mahato",
      "constituency": "TUNDI",
      "state": "Jharkhand",
      "stateSlug": "jharkhand",
      "party": "JMM",
      "criminalCases": 0,
      "education": "10th Pass",
      "assets": 45054633,
      "liabilities": 6160184,
      "sourceUrl": "https://myneta.info/Jharkhand2024/candidate.php?candidate_id=828",
      "prs": null,
      "photoUrl": "https://myneta.info/images_candidate/Jharkhand2024/ba364625c303c2bd1f68d54ef8fe3c660eb113a9.jpg"
    },
    {
      "id": "888",
      "name": "Md. Tajuddin",
      "constituency": "RAJMAHAL",
      "state": "Jharkhand",
      "stateSlug": "jharkhand",
      "party": "JMM",
      "criminalCases": 1,
      "education": "12th Pass",
      "assets": 193939135,
      "liabilities": 89519267,
      "sourceUrl": "https://myneta.info/Jharkhand2024/candidate.php?candidate_id=888",
      "prs": null,
      "photoUrl": "https://myneta.info/images_candidate/Jharkhand2024/f0b2e38564b9b8832f595c8c4dc36539d953ad24.jpg"
    },
    {
      "id": "841",
      "name": "Nagendra Mahto",
      "constituency": "BAGODAR",
      "state": "Jharkhand",
      "stateSlug": "jharkhand",
      "party": "BJP",
      "criminalCases": 0,
      "education": "Graduate",
      "assets": 30702583,
      "liabilities": 0,
      "sourceUrl": "https://myneta.info/Jharkhand2024/candidate.php?candidate_id=841",
      "prs": null,
      "photoUrl": "https://myneta.info/images_candidate/Jharkhand2024/3acedc5b450699a25465b71664bf06f111f97097.jpg"
    },
    {
      "id": "381",
      "name": "Naman Bixal Kongari",
      "constituency": "KOLEBIRA (ST)",
      "state": "Jharkhand",
      "stateSlug": "jharkhand",
      "party": "INC",
      "criminalCases": 1,
      "education": "Graduate Professional",
      "assets": 13399046,
      "liabilities": 0,
      "sourceUrl": "https://myneta.info/Jharkhand2024/candidate.php?candidate_id=381",
      "prs": null,
      "photoUrl": "https://myneta.info/images_candidate/Jharkhand2024/cac04562f8110b31d16ba1344d8a5a93fa067721.jpg"
    },
    {
      "id": "347",
      "name": "Navin Jaiswal",
      "constituency": "HATIA",
      "state": "Jharkhand",
      "stateSlug": "jharkhand",
      "party": "BJP",
      "criminalCases": 3,
      "education": "Graduate",
      "assets": 184236000,
      "liabilities": 88630000,
      "sourceUrl": "https://myneta.info/Jharkhand2024/candidate.php?candidate_id=347",
      "prs": null,
      "photoUrl": "https://myneta.info/images_candidate/Jharkhand2024/079059fd1c45074e606495d87659ee9aa1c52135.jpg"
    },
    {
      "id": "403",
      "name": "Niral Purty",
      "constituency": "MAJHGAON (ST)",
      "state": "Jharkhand",
      "stateSlug": "jharkhand",
      "party": "JMM",
      "criminalCases": 0,
      "education": "12th Pass",
      "assets": 37146908,
      "liabilities": 0,
      "sourceUrl": "https://myneta.info/Jharkhand2024/candidate.php?candidate_id=403",
      "prs": null,
      "photoUrl": "https://myneta.info/images_candidate/Jharkhand2024/193ea4d0e10be2becd815aa71a5ff7656f83e086.jpg"
    },
    {
      "id": "866",
      "name": "Nirmal Mahto",
      "constituency": "MANDU",
      "state": "Jharkhand",
      "stateSlug": "jharkhand",
      "party": "AJSU Party",
      "criminalCases": 10,
      "education": "10th Pass",
      "assets": 58023061,
      "liabilities": 9106804,
      "sourceUrl": "https://myneta.info/Jharkhand2024/candidate.php?candidate_id=866",
      "prs": null,
      "photoUrl": "https://myneta.info/images_candidate/Jharkhand2024/7750411202264ea4cc6bb79560d0eba679dad088.jpg"
    },
    {
      "id": "958",
      "name": "Pradeep Yadav",
      "constituency": "POREYAHAT",
      "state": "Jharkhand",
      "stateSlug": "jharkhand",
      "party": "INC",
      "criminalCases": 5,
      "education": "Graduate",
      "assets": 16590986,
      "liabilities": 0,
      "sourceUrl": "https://myneta.info/Jharkhand2024/candidate.php?candidate_id=958",
      "prs": null,
      "photoUrl": "https://myneta.info/images_candidate/Jharkhand2024/f453882cf63ef435b2454878f09fe2708b14026b.jpg"
    },
    {
      "id": "262",
      "name": "Pradip Prasad",
      "constituency": "HAZARIBAGH",
      "state": "Jharkhand",
      "stateSlug": "jharkhand",
      "party": "BJP",
      "criminalCases": 2,
      "education": "Graduate",
      "assets": 66937567,
      "liabilities": 12850000,
      "sourceUrl": "https://myneta.info/Jharkhand2024/candidate.php?candidate_id=262",
      "prs": null,
      "photoUrl": "https://myneta.info/images_candidate/Jharkhand2024/9011a76e34facb3708dfd7641b99a2337f15f64b.jpg"
    },
    {
      "id": "283",
      "name": "Prakash Ram",
      "constituency": "LATEHAR (SC)",
      "state": "Jharkhand",
      "stateSlug": "jharkhand",
      "party": "BJP",
      "criminalCases": 0,
      "education": "Post Graduate",
      "assets": 48865845,
      "liabilities": 17709744,
      "sourceUrl": "https://myneta.info/Jharkhand2024/candidate.php?candidate_id=283",
      "prs": null,
      "photoUrl": "https://myneta.info/images_candidate/Jharkhand2024/c3a6f2911a35eca54bd6cc7da667e677f9e7095b.jpg"
    },
    {
      "id": "418",
      "name": "Purnima Sahu",
      "constituency": "JAMSHEDPUR EAST",
      "state": "Jharkhand",
      "stateSlug": "jharkhand",
      "party": "BJP",
      "criminalCases": 0,
      "education": "Graduate",
      "assets": 17599942,
      "liabilities": 0,
      "sourceUrl": "https://myneta.info/Jharkhand2024/candidate.php?candidate_id=418",
      "prs": null,
      "photoUrl": "https://myneta.info/images_candidate/Jharkhand2024/a0b9a6bf5e654f30e753387a5cbca97d13b4056a.jpg"
    },
    {
      "id": "868",
      "name": "Rabindra Nath Mahato",
      "constituency": "NALA",
      "state": "Jharkhand",
      "stateSlug": "jharkhand",
      "party": "JMM",
      "criminalCases": 0,
      "education": "Doctorate",
      "assets": 17792465,
      "liabilities": 74142,
      "sourceUrl": "https://myneta.info/Jharkhand2024/candidate.php?candidate_id=868",
      "prs": null,
      "photoUrl": "https://myneta.info/images_candidate/Jharkhand2024/9f3e12ef61711114c09d2c31101fc33e30e5440a.jpg"
    },
    {
      "id": "661",
      "name": "Radha Krishana Kishore",
      "constituency": "CHHATARPUR (SC)",
      "state": "Jharkhand",
      "stateSlug": "jharkhand",
      "party": "INC",
      "criminalCases": 0,
      "education": "Graduate",
      "assets": 31028424,
      "liabilities": 1283740,
      "sourceUrl": "https://myneta.info/Jharkhand2024/candidate.php?candidate_id=661",
      "prs": null,
      "photoUrl": "https://myneta.info/images_candidate/Jharkhand2024/1ebcabcb7b13b8b0b5e73c17bacfe1654bca7f0e.jpg"
    },
    {
      "id": "1031",
      "name": "Ragini Singh",
      "constituency": "JHARIA",
      "state": "Jharkhand",
      "stateSlug": "jharkhand",
      "party": "BJP",
      "criminalCases": 0,
      "education": "Literate",
      "assets": 99841846,
      "liabilities": 16392975,
      "sourceUrl": "https://myneta.info/Jharkhand2024/candidate.php?candidate_id=1031",
      "prs": null,
      "photoUrl": "https://myneta.info/images_candidate/Jharkhand2024/a424f71a5160944043c6fc0d937d4fa054cd51f4.jpg"
    },
    {
      "id": "823",
      "name": "Raj Sinha",
      "constituency": "DHANBAD",
      "state": "Jharkhand",
      "stateSlug": "jharkhand",
      "party": "BJP",
      "criminalCases": 1,
      "education": "Post Graduate",
      "assets": 35422609,
      "liabilities": 611667,
      "sourceUrl": "https://myneta.info/Jharkhand2024/candidate.php?candidate_id=823",
      "prs": null,
      "photoUrl": "https://myneta.info/images_candidate/Jharkhand2024/793cbfa03604b44f6de5b1b18589f8d572888058.jpg"
    },
    {
      "id": "885",
      "name": "Rajesh Kachhap",
      "constituency": "KHIJRI (ST)",
      "state": "Jharkhand",
      "stateSlug": "jharkhand",
      "party": "INC",
      "criminalCases": 0,
      "education": "Graduate",
      "assets": 37039879,
      "liabilities": 5900000,
      "sourceUrl": "https://myneta.info/Jharkhand2024/candidate.php?candidate_id=885",
      "prs": null,
      "photoUrl": "https://myneta.info/images_candidate/Jharkhand2024/435ef15318c8f7ceae5e545ff3b6c4e6c71014cb.jpg"
    },
    {
      "id": "79",
      "name": "Ram Das Soren",
      "constituency": "GHATSILA (ST)",
      "state": "Jharkhand",
      "stateSlug": "jharkhand",
      "party": "JMM",
      "criminalCases": 2,
      "education": "Graduate",
      "assets": 104555586,
      "liabilities": 3293952,
      "sourceUrl": "https://myneta.info/Jharkhand2024/candidate.php?candidate_id=79",
      "prs": null,
      "photoUrl": "https://myneta.info/images_candidate/Jharkhand2024/4238d4c37b98782b98435bafca62b9d8504bb876.jpg"
    },
    {
      "id": "605",
      "name": "Ram Surya Munda",
      "constituency": "KHUNTI (ST)",
      "state": "Jharkhand",
      "stateSlug": "jharkhand",
      "party": "JMM",
      "criminalCases": 0,
      "education": "12th Pass",
      "assets": 5345000,
      "liabilities": 800000,
      "sourceUrl": "https://myneta.info/Jharkhand2024/candidate.php?candidate_id=605",
      "prs": null,
      "photoUrl": "https://myneta.info/images_candidate/Jharkhand2024/3a46cd6e240d96259b131deb97456de0610739f9.jpg"
    },
    {
      "id": "278",
      "name": "Ramchandra Singh",
      "constituency": "MANIKA (ST)",
      "state": "Jharkhand",
      "stateSlug": "jharkhand",
      "party": "INC",
      "criminalCases": 0,
      "education": "Graduate",
      "assets": 16413515,
      "liabilities": 2239500,
      "sourceUrl": "https://myneta.info/Jharkhand2024/candidate.php?candidate_id=278",
      "prs": null,
      "photoUrl": "https://myneta.info/images_candidate/Jharkhand2024/211458c2f066a02b04af2913444f10328d3c49f4.jpg"
    },
    {
      "id": "289",
      "name": "Rameshwar Oraon",
      "constituency": "LOHARDAGA (ST)",
      "state": "Jharkhand",
      "stateSlug": "jharkhand",
      "party": "INC",
      "criminalCases": 0,
      "education": "Doctorate",
      "assets": 422035795,
      "liabilities": 1943437,
      "sourceUrl": "https://myneta.info/Jharkhand2024/candidate.php?candidate_id=289",
      "prs": null,
      "photoUrl": "https://myneta.info/images_candidate/Jharkhand2024/c5775044694f219185c3e19c212cb5e83e6c5616.jpg"
    },
    {
      "id": "167",
      "name": "Roshan Lal Choudhary",
      "constituency": "BARKAGAON",
      "state": "Jharkhand",
      "stateSlug": "jharkhand",
      "party": "BJP",
      "criminalCases": 0,
      "education": "Graduate",
      "assets": 17687464,
      "liabilities": 7545571,
      "sourceUrl": "https://myneta.info/Jharkhand2024/candidate.php?candidate_id=167",
      "prs": null,
      "photoUrl": "https://myneta.info/images_candidate/Jharkhand2024/38b5a7ca2eca621dfeb654ff3febea37d6011a24.jpg"
    },
    {
      "id": "51",
      "name": "Sabita Mahato",
      "constituency": "ICHAGARH",
      "state": "Jharkhand",
      "stateSlug": "jharkhand",
      "party": "JMM",
      "criminalCases": 0,
      "education": "8th Pass",
      "assets": 68855267,
      "liabilities": 3334,
      "sourceUrl": "https://myneta.info/Jharkhand2024/candidate.php?candidate_id=51",
      "prs": null,
      "photoUrl": "https://myneta.info/images_candidate/Jharkhand2024/26831e3a4f11f84c00f5a0e5d94d167c40391701.jpg"
    },
    {
      "id": "183",
      "name": "Samir Kumar Mohanty",
      "constituency": "BAHARAGORA",
      "state": "Jharkhand",
      "stateSlug": "jharkhand",
      "party": "JMM",
      "criminalCases": 2,
      "education": "Graduate",
      "assets": 4936392,
      "liabilities": 1176660,
      "sourceUrl": "https://myneta.info/Jharkhand2024/candidate.php?candidate_id=183",
      "prs": null,
      "photoUrl": "https://myneta.info/images_candidate/Jharkhand2024/7f221f41b2d09b0feccee2aca1ab534c63e97c9f.jpg"
    },
    {
      "id": "324",
      "name": "Sanjay Kumar Singh Yadav",
      "constituency": "HUSSAINABAD",
      "state": "Jharkhand",
      "stateSlug": "jharkhand",
      "party": "RJD",
      "criminalCases": 3,
      "education": "10th Pass",
      "assets": 155989180,
      "liabilities": 1999190,
      "sourceUrl": "https://myneta.info/Jharkhand2024/candidate.php?candidate_id=324",
      "prs": null,
      "photoUrl": "https://myneta.info/images_candidate/Jharkhand2024/43c32efbd601da2f999a2a95a849c98a6d38a32f.jpg"
    },
    {
      "id": "1175",
      "name": "Sanjay Prasad Yadav",
      "constituency": "GODDA",
      "state": "Jharkhand",
      "stateSlug": "jharkhand",
      "party": "RJD",
      "criminalCases": 6,
      "education": "12th Pass",
      "assets": 295997350,
      "liabilities": 48947842,
      "sourceUrl": "https://myneta.info/Jharkhand2024/candidate.php?candidate_id=1175",
      "prs": null,
      "photoUrl": "https://myneta.info/images_candidate/Jharkhand2024/b5e7860f02d98f2dd2bee47450f6037241085754.jpg"
    },
    {
      "id": "13",
      "name": "Sanjib Sardar",
      "constituency": "POTKA (ST)",
      "state": "Jharkhand",
      "stateSlug": "jharkhand",
      "party": "JMM",
      "criminalCases": 3,
      "education": "12th Pass",
      "assets": 16569215,
      "liabilities": 2029800,
      "sourceUrl": "https://myneta.info/Jharkhand2024/candidate.php?candidate_id=13",
      "prs": null,
      "photoUrl": "https://myneta.info/images_candidate/Jharkhand2024/43caa2f61370ba80b88fe332c69caebcc2715628.jpg"
    },
    {
      "id": "214",
      "name": "Saryu Roy",
      "constituency": "JAMSHEDPUR WEST",
      "state": "Jharkhand",
      "stateSlug": "jharkhand",
      "party": "JD(U)",
      "criminalCases": 4,
      "education": "Post Graduate",
      "assets": 45685402,
      "liabilities": 1920600,
      "sourceUrl": "https://myneta.info/Jharkhand2024/candidate.php?candidate_id=214",
      "prs": null,
      "photoUrl": "https://myneta.info/images_candidate/Jharkhand2024/41321e792ee8ffae3e9db09663dfc24987e5b81b.jpg"
    },
    {
      "id": "61",
      "name": "Satyendra Nath Tiwari",
      "constituency": "GARHWA",
      "state": "Jharkhand",
      "stateSlug": "jharkhand",
      "party": "BJP",
      "criminalCases": 7,
      "education": "Graduate",
      "assets": 38480206,
      "liabilities": 1970552,
      "sourceUrl": "https://myneta.info/Jharkhand2024/candidate.php?candidate_id=61",
      "prs": null,
      "photoUrl": "https://myneta.info/images_candidate/Jharkhand2024/7da23820c963ff02b076c51a2276a8b2171b3049.jpg"
    },
    {
      "id": "1022",
      "name": "Shatrughan Mahto",
      "constituency": "BAGHMARA",
      "state": "Jharkhand",
      "stateSlug": "jharkhand",
      "party": "BJP",
      "criminalCases": 4,
      "education": "12th Pass",
      "assets": 135968603,
      "liabilities": 81730572,
      "sourceUrl": "https://myneta.info/Jharkhand2024/candidate.php?candidate_id=1022",
      "prs": null,
      "photoUrl": "https://myneta.info/images_candidate/Jharkhand2024/52b5fe8e9d39191828c67cd1f2f98b15c547e5b9.jpg"
    },
    {
      "id": "353",
      "name": "Shilpi Neha Tirkey",
      "constituency": "MANDAR (ST)",
      "state": "Jharkhand",
      "stateSlug": "jharkhand",
      "party": "INC",
      "criminalCases": 1,
      "education": "Graduate",
      "assets": 19055845,
      "liabilities": 176951,
      "sourceUrl": "https://myneta.info/Jharkhand2024/candidate.php?candidate_id=353",
      "prs": null,
      "photoUrl": "https://myneta.info/images_candidate/Jharkhand2024/e1afe00f5d0335ca066b302d7296347c2ac457e4.jpg"
    },
    {
      "id": "1354",
      "name": "Shwettaa Singh",
      "constituency": "BOKARO",
      "state": "Jharkhand",
      "stateSlug": "jharkhand",
      "party": "INC",
      "criminalCases": 0,
      "education": "Graduate",
      "assets": 6894529,
      "liabilities": 3218828,
      "sourceUrl": "https://myneta.info/Jharkhand2024/candidate.php?candidate_id=1354",
      "prs": null,
      "photoUrl": "https://myneta.info/images_candidate/Jharkhand2024/d65622230b4baeafa63d170fef5c8af2d249d768.jpg"
    },
    {
      "id": "1389",
      "name": "Somesh Chandra Soren",
      "constituency": "GHATSILA (ST) : BYE ELECTION ON 11-11-2025",
      "state": "Jharkhand",
      "stateSlug": "jharkhand",
      "party": "JMM",
      "criminalCases": 0,
      "education": "Graduate Professional",
      "assets": 6870091,
      "liabilities": 1429507,
      "sourceUrl": "https://myneta.info/Jharkhand2024/candidate.php?candidate_id=1389",
      "prs": null,
      "photoUrl": "https://myneta.info/images_candidate/Jharkhand2024/2d497be178c47f49016f73878428df95756a9cfd.jpg"
    },
    {
      "id": "142",
      "name": "Sona Ram Sinku",
      "constituency": "JAGANATHPUR (ST)",
      "state": "Jharkhand",
      "stateSlug": "jharkhand",
      "party": "INC",
      "criminalCases": 0,
      "education": "10th Pass",
      "assets": 22555427,
      "liabilities": 1289324,
      "sourceUrl": "https://myneta.info/Jharkhand2024/candidate.php?candidate_id=142",
      "prs": null,
      "photoUrl": "https://myneta.info/images_candidate/Jharkhand2024/aa76c33a41a58097c648950dfe6b17c89eea2a91.jpg"
    },
    {
      "id": "980",
      "name": "Stephen Marandi",
      "constituency": "MAHESHPUR (ST)",
      "state": "Jharkhand",
      "stateSlug": "jharkhand",
      "party": "JMM",
      "criminalCases": 1,
      "education": "Post Graduate",
      "assets": 51465670,
      "liabilities": 0,
      "sourceUrl": "https://myneta.info/Jharkhand2024/candidate.php?candidate_id=980",
      "prs": null,
      "photoUrl": "https://myneta.info/images_candidate/Jharkhand2024/ba27aaa8a2810e840e7143a1459a1c718a5d9195.jpg"
    },
    {
      "id": "160",
      "name": "Sudeep Gudhiya",
      "constituency": "TORPA (ST)",
      "state": "Jharkhand",
      "stateSlug": "jharkhand",
      "party": "JMM",
      "criminalCases": 0,
      "education": "Graduate Professional",
      "assets": 5762845,
      "liabilities": 45849,
      "sourceUrl": "https://myneta.info/Jharkhand2024/candidate.php?candidate_id=160",
      "prs": null,
      "photoUrl": "https://myneta.info/images_candidate/Jharkhand2024/0ecc0a169e4181012f14bdba273ea8e2d5612a7e.jpg"
    },
    {
      "id": "783",
      "name": "Sukhram Oraon",
      "constituency": "CHAKRADHARPUR (ST)",
      "state": "Jharkhand",
      "stateSlug": "jharkhand",
      "party": "JMM",
      "criminalCases": 0,
      "education": "Post Graduate",
      "assets": 44861371,
      "liabilities": 4038170,
      "sourceUrl": "https://myneta.info/Jharkhand2024/candidate.php?candidate_id=783",
      "prs": null,
      "photoUrl": "https://myneta.info/images_candidate/Jharkhand2024/19f3f0e3034eec87d3a068b017941276c2d47165.jpg"
    },
    {
      "id": "715",
      "name": "Suresh Kumar Baitha",
      "constituency": "KANKE (SC)",
      "state": "Jharkhand",
      "stateSlug": "jharkhand",
      "party": "INC",
      "criminalCases": 1,
      "education": "Post Graduate",
      "assets": 10411704,
      "liabilities": 0,
      "sourceUrl": "https://myneta.info/Jharkhand2024/candidate.php?candidate_id=715",
      "prs": null,
      "photoUrl": "https://myneta.info/images_candidate/Jharkhand2024/ad76e77d17fceeef2f00194d610af7d205a593b6.jpg"
    },
    {
      "id": "932",
      "name": "Suresh Paswan",
      "constituency": "DEOGHAR (SC)",
      "state": "Jharkhand",
      "stateSlug": "jharkhand",
      "party": "RJD",
      "criminalCases": 3,
      "education": "8th Pass",
      "assets": 187678000,
      "liabilities": 5198347,
      "sourceUrl": "https://myneta.info/Jharkhand2024/candidate.php?candidate_id=932",
      "prs": null,
      "photoUrl": "https://myneta.info/images_candidate/Jharkhand2024/ada4131d6d6c78541e21ab66f7eae6246e118533.jpg"
    },
    {
      "id": "924",
      "name": "Uday Shankar Singh",
      "constituency": "SARATH",
      "state": "Jharkhand",
      "stateSlug": "jharkhand",
      "party": "JMM",
      "criminalCases": 0,
      "education": "12th Pass",
      "assets": 117230861,
      "liabilities": 2512808,
      "sourceUrl": "https://myneta.info/Jharkhand2024/candidate.php?candidate_id=924",
      "prs": null,
      "photoUrl": "https://myneta.info/images_candidate/Jharkhand2024/c77ce35e3f88a01f51a57f96fc32b4f9796d83de.jpg"
    },
    {
      "id": "813",
      "name": "Uma Kant Rajak",
      "constituency": "CHANDANKIYARI (SC)",
      "state": "Jharkhand",
      "stateSlug": "jharkhand",
      "party": "JMM",
      "criminalCases": 0,
      "education": "10th Pass",
      "assets": 15792982,
      "liabilities": 5760000,
      "sourceUrl": "https://myneta.info/Jharkhand2024/candidate.php?candidate_id=813",
      "prs": null,
      "photoUrl": "https://myneta.info/images_candidate/Jharkhand2024/2b39fa399ba8264b4905d4a12d4aa729b5f5501f.jpg"
    },
    {
      "id": "333",
      "name": "Vikas Kumar Munda",
      "constituency": "TAMAR (ST)",
      "state": "Jharkhand",
      "stateSlug": "jharkhand",
      "party": "JMM",
      "criminalCases": 0,
      "education": "Graduate",
      "assets": 11832585,
      "liabilities": 0,
      "sourceUrl": "https://myneta.info/Jharkhand2024/candidate.php?candidate_id=333",
      "prs": null,
      "photoUrl": "https://myneta.info/images_candidate/Jharkhand2024/a1c683c0221e29c45ac724d4387dc2b9e3c78a8f.jpg"
    },
    {
      "id": "804",
      "name": "Yogendra Prasad",
      "constituency": "GOMIA",
      "state": "Jharkhand",
      "stateSlug": "jharkhand",
      "party": "JMM",
      "criminalCases": 0,
      "education": "Graduate",
      "assets": 18497230,
      "liabilities": 770000,
      "sourceUrl": "https://myneta.info/Jharkhand2024/candidate.php?candidate_id=804",
      "prs": null,
      "photoUrl": "https://myneta.info/images_candidate/Jharkhand2024/2b5cc992a30a302e71ed153283f07a277c68487a.jpg"
    }
  ]
}